{"index.md":"DuRmMlyp","sentinelexplorer_index.md":"HjQsmm3U","software-services_datamodel_index.md":"DvptrQIh","software-services_datamodel_technical-deep-dive.md":"D0cXAihG","software-services_eodash_dashboard.md":"DJJXKPY_","software-services_eodash_index.md":"Blll91WE","software-services_eoxelements_advanced.md":"DeVbwfUP","software-services_eoxelements_basic.md":"BjlSHzBY","software-services_eoxelements_globe.md":"B1v5PKKi","software-services_eoxelements_index.md":"vgmXUlsx","software-services_eoxelements_story.md":"B2V3WwM6","software-services_index.md":"jgUbah43","software-services_ol_basic.md":"DnNyzdRJ","software-services_ol_index.md":"DxwNMMdL","software-services_ol_ndvi.md":"BIv0T5lK","software-services_ol_stac.md":"BrwnFYLG","software-services_titiler_crop.md":"DBCSH_dT","software-services_titiler_index.md":"BgdkyoBg","software-services_titiler_ndvi.md":"CRb49tNN","software-services_titiler_rgb.md":"C9i2DgOa","software_ol_stac-demo.md":"C51B-x-a","story_index.md":"DVqdbquk"}
