{"datamodel_index.md":"Cx9ecGek","datamodel_technical-deep-dive.md":"BCtwVh9S","index.md":"DjrPMpQP","sentinelexplorer_index.md":"x9MUjwJD","software-services.md":"BZgwphFV","software_ol.md":"B4fZznml","software_ol_basic.md":"BaxgcUmV","software_ol_ndvi.md":"C6numgHu","software_ol_stac-demo.md":"CDYC-V5X","software_ol_stac.md":"B6dJSX_6","software_titiler.md":"CPS8IzV3","software_titiler_crop.md":"BKUALRNU","software_titiler_ndvi.md":"Cwidzcgh","software_titiler_rgb.md":"ziPLpYW2","story_index.md":"DQLt9H9B"}
